generate_keys.py
generate_keys-1.0.0.dist-info/DESCRIPTION.rst
generate_keys-1.0.0.dist-info/METADATA
generate_keys-1.0.0.dist-info/RECORD
generate_keys-1.0.0.dist-info/WHEEL
generate_keys-1.0.0.dist-info/entry_points.txt
generate_keys-1.0.0.dist-info/metadata.json
generate_keys-1.0.0.dist-info/top_level.txt
