Metadata-Version: 2.0
Name: generate-keys
Version: 1.0.0
Summary: Util for generating public and private rsa keys.
Home-page: UNKNOWN
Author: EPAM Systems
Author-email: UNKNOWN
License: Apache License 2.0
Platform: UNKNOWN
Requires-Dist: pyopenssl
